ykenan_util/__init__.py
ykenan_util/snowflake.py
ykenan_util-0.0.7.dist-info/LICENSE
ykenan_util-0.0.7.dist-info/METADATA
ykenan_util-0.0.7.dist-info/WHEEL
ykenan_util-0.0.7.dist-info/top_level.txt
ykenan_util-0.0.7.dist-info/RECORD
